AUTHORS.rst
CONTRIBUTING.rst
HISTORY.rst
LICENSE
MANIFEST.in
README.rst
setup.cfg
setup.py
andablog/__init__.py
andablog/admin.py
andablog/feeds.py
andablog/models.py
andablog/sitemaps.py
andablog/urls.py
andablog/views.py
andablog/migrations/0001_initial.py
andablog/migrations/0002_auto_20141204_1659.py
andablog/migrations/0003_auto_20150826_2353.py
andablog/migrations/0004_shorten_entry_title.py
andablog/migrations/0005_auto_20151017_1747.py
andablog/migrations/0006_auto_20170609_1759.py
andablog/migrations/0007_auto_20190315_1540.py
andablog/migrations/__init__.py
andablog/static/css/andablog.css
andablog/static/img/.gitignore
andablog/static/js/djangoandablog.js
andablog/templates/base.html
andablog/templates/andablog/base.html
andablog/templates/andablog/comments_count_snippet.html
andablog/templates/andablog/comments_snippet.html
andablog/templates/andablog/entry_detail.html
andablog/templates/andablog/entry_list.html
andablog/templates/andablog/pagination_snippet.html
andablog/templatetags/__init__.py
andablog/templatetags/andablog_tags.py
andablog/tests/__init__.py
andablog/tests/test_entry_detail.py
andablog/tests/test_entry_forms.py
andablog/tests/test_entry_listing.py
andablog/tests/test_feeds.py
andablog/tests/test_models.py
andablog/tests/test_sitemaps.py
andablog/tests/test_templatetags.py
demo/db.sqlite3
demo/manage.py
demo/blog/__init__.py
demo/blog/admin.py
demo/blog/feeds.py
demo/blog/models.py
demo/blog/tests.py
demo/blog/urls.py
demo/blog/views.py
demo/blog/fixtures/tags_for_three_entries.json
demo/blog/fixtures/three_published_entries.json
demo/blog/migrations/__init__.py
demo/common/__init__.py
demo/common/admin.py
demo/common/forms.py
demo/common/models.py
demo/common/tests.py
demo/common/fixtures/admin_user.json
demo/common/fixtures/one_user.json
demo/common/fixtures/three_users.json
demo/common/management/__init__.py
demo/common/management/commands/__init__.py
demo/common/management/commands/check_missing_migrations.py
django_andablog.egg-info/PKG-INFO
django_andablog.egg-info/SOURCES.txt
django_andablog.egg-info/dependency_links.txt
django_andablog.egg-info/not-zip-safe
django_andablog.egg-info/requires.txt
django_andablog.egg-info/top_level.txt
