Metadata-Version: 1.1
Name: django-andablog
Version: 3.1.0
Summary: A blog app that is only intended to be embedded within an existing Django site.
Home-page: https://github.com/WimpyAnalytics/django-andablog
Author: Ivan VenOsdel
Author-email: ivan@wimpyanalytics.com
License: BSD
Download-URL: https://github.com/wimpyanalytics/django-andablog/tarball/3.1.0
Keywords: django-andablog,blog,django,app,reusable app,andablog
Platform: UNKNOWN
Classifier: Development Status :: 5 - Production/Stable
Classifier: Intended Audience :: Developers
Classifier: License :: OSI Approved :: BSD License
Classifier: Natural Language :: English
Classifier: Programming Language :: Python :: 3 :: Only
Classifier: Framework :: Django
